pds3_utils.py
pds3_utils-0.1.dist-info/METADATA
pds3_utils-0.1.dist-info/WHEEL
pds3_utils-0.1.dist-info/top_level.txt
pds3_utils-0.1.dist-info/RECORD
