Metadata-Version: 2.4
Name: pds3_utils
Version: 0.1
Summary: A set of utilities to analyse PDS3 meta-data
Home-page: https://github.com/msbentley/pds3_utils
Download-URL: https://github.com/msbentley/pds3_utils/archive/0.1.tar.gz
Author: Mark S. Bentley
Author-email: mark@lunartech.org
Keywords: PDS,PDS3,planetary
Requires-Python: >=3.0
Requires-Dist: pandas
Requires-Dist: pyyaml
Requires-Dist: pvl
Dynamic: author
Dynamic: author-email
Dynamic: description
Dynamic: description-content-type
Dynamic: download-url
Dynamic: home-page
Dynamic: keywords
Dynamic: requires-dist
Dynamic: requires-python
Dynamic: summary
